mloda/core/__init__.py
mloda/core/py.typed
mloda/core/abstract_plugins/__init__.py
mloda/core/abstract_plugins/compute_framework.py
mloda/core/abstract_plugins/feature_group.py
mloda/core/abstract_plugins/function_extender.py
mloda/core/abstract_plugins/components/__init__.py
mloda/core/abstract_plugins/components/base_artifact.py
mloda/core/abstract_plugins/components/base_feature_group_version.py
mloda/core/abstract_plugins/components/base_validator.py
mloda/core/abstract_plugins/components/data_access_collection.py
mloda/core/abstract_plugins/components/data_types.py
mloda/core/abstract_plugins/components/domain.py
mloda/core/abstract_plugins/components/feature.py
mloda/core/abstract_plugins/components/feature_collection.py
mloda/core/abstract_plugins/components/feature_name.py
mloda/core/abstract_plugins/components/feature_set.py
mloda/core/abstract_plugins/components/hashable_dict.py
mloda/core/abstract_plugins/components/link.py
mloda/core/abstract_plugins/components/options.py
mloda/core/abstract_plugins/components/parallelization_modes.py
mloda/core/abstract_plugins/components/utils.py
mloda/core/abstract_plugins/components/feature_chainer/__init__.py
mloda/core/abstract_plugins/components/feature_chainer/feature_chain_parser.py
mloda/core/abstract_plugins/components/feature_chainer/feature_chain_parser_mixin.py
mloda/core/abstract_plugins/components/framework_transformer/__init__.py
mloda/core/abstract_plugins/components/framework_transformer/base_transformer.py
mloda/core/abstract_plugins/components/framework_transformer/cfw_transformer.py
mloda/core/abstract_plugins/components/index/__init__.py
mloda/core/abstract_plugins/components/index/add_index_feature.py
mloda/core/abstract_plugins/components/index/index.py
mloda/core/abstract_plugins/components/input_data/__init__.py
mloda/core/abstract_plugins/components/input_data/base_input_data.py
mloda/core/abstract_plugins/components/input_data/api/__init__.py
mloda-0.4.3.dist-info/licenses/LICENSE.TXT
mloda-0.4.3.dist-info/licenses/NOTICE.md
mloda-0.4.3.dist-info/METADATA
mloda-0.4.3.dist-info/WHEEL
mloda-0.4.3.dist-info/entry_points.txt
mloda-0.4.3.dist-info/top_level.txt
mloda-0.4.3.dist-info/RECORD
