Metadata-Version: 2.4
Name: mloda
Version: 0.4.3
Summary: mloda: One Data Access for ML and AI
Author-email: Tom Kaltofen <info@mloda.ai>
License: Apache-2.0
Project-URL: Bug Tracker, https://github.com/mloda-ai/mloda/issues
Project-URL: Documentation, https://mloda-ai.github.io/mloda/
Project-URL: Source Code, https://github.com/mloda-ai/mloda
Project-URL: PyPI, https://pypi.org/project/mloda/
Project-URL: Homepage, https://mloda.ai
Classifier: Programming Language :: Python :: 3
Requires-Python: <3.14,>=3.8
License-File: LICENSE.TXT
License-File: NOTICE.md
Requires-Dist: pyarrow
Dynamic: license-file
